{
    "runs_on": [
        "Mac",
        "Linux",
        "Windows"
    ],
    "download_link": "",
    "available_on_deken": true,
    "bug_reports": "https://github.com/porres/pd-else/issues",
    "developers": [
        "Alexandre Torres Porres"
    ],
    "part_of_library": true,
    "library_name": "else",
    "articles": [],
    "videos": [],
    "musics": [],
    "contributors": [
        "charlesneimog"
    ],
    "ai": true,
    "title": "scales",
    "description": "The `scales` object generates musical scales based on a list of semitone intervals, outputting them as note names or MIDI pitches. It allows specifying a starting note, octave, and can be configured to output MIDI pitch values using the `-pitch` flag.",
    "categories": [
        "MIDI"
    ]
}