{
    "runs_on": [
        "Mac",
        "Linux",
        "Windows"
    ],
    "download_link": "",
    "available_on_deken": true,
    "bug_reports": "https://github.com/porres/pd-else/issues",
    "developers": [
        "Alexandre Torres Porres"
    ],
    "part_of_library": true,
    "library_name": "else",
    "articles": [],
    "videos": [],
    "musics": [],
    "contributors": [
        "charlesneimog"
    ],
    "ai": true,
    "title": "rec",
    "description": "The `rec` object records incoming messages across multiple tracks and plays them back. It supports up to 64 tracks, with each inlet corresponding to a track for recording and each outlet for playback. It can record, play, mute, and save/load messages from text files, making it useful for message sequencing and automation.",
    "categories": [
        "Procedural",
        "Sequencers",
        "File I/O"
    ]
}